PygameTemplates
