Metadata-Version: 1.1
Name: PygameTemplates
Version: 0.1.0
Summary: An easy way to add templates to a pygame script
Home-page: UNKNOWN
Author: Thomas Blume
Author-email: tblume10@yahoo.com
License: MIT
Keywords: pygame
Platform: UNKNOWN
Classifier: Development Status :: 5 - Production/Stable
Classifier: Intended Audience :: Education
Classifier: Operating System :: Microsoft :: Windows :: Windows 10
Classifier: License :: OSI Approved :: MIT License
Classifier: Programming Language :: Python :: 3
